phpmyadmin/__init__.py
phpmyadmin/phpmyadmin.py
phpmyadmin/support/__init__.py
phpmyadmin/support/config_reader.py
phpmyadmin/support/docker_functions.py
phpmyadmin-0.0.1.dist-info/DESCRIPTION.rst
phpmyadmin-0.0.1.dist-info/METADATA
phpmyadmin-0.0.1.dist-info/RECORD
phpmyadmin-0.0.1.dist-info/WHEEL
phpmyadmin-0.0.1.dist-info/entry_points.txt
phpmyadmin-0.0.1.dist-info/metadata.json
phpmyadmin-0.0.1.dist-info/top_level.txt
