Metadata-Version: 1.1
Name: phpmyadmin
Version: 0.0.1
Summary: Phpmyadmin docker server
Home-page: https://github.com/iBoneYard/phpmyadmin
Author: indrajit
Author-email: eendroroy@gmail.com
License: MIT
Keywords: phpmyadmin docker mysql mariadb
Platform: UNKNOWN
Classifier: Development Status :: 3 - Alpha
Classifier: Intended Audience :: Developers
Classifier: Topic :: Software Development :: Build Tools
Classifier: License :: OSI Approved :: MIT License
Classifier: Programming Language :: Python :: 2
Classifier: Programming Language :: Python :: 2.7
Classifier: Programming Language :: Python :: 3
Classifier: Programming Language :: Python :: 3.3
Classifier: Programming Language :: Python :: 3.4
Classifier: Programming Language :: Python :: 3.5
